.gitignore
MANIFEST.in
README.rst
setup.cfg
setup.py
docs/HISTORY.txt
docs/LICENSE.GPL
docs/LICENSE.txt
docs/MANUAL.txt
raptus/__init__.py
raptus.article.gallery.egg-info/PKG-INFO
raptus.article.gallery.egg-info/SOURCES.txt
raptus.article.gallery.egg-info/dependency_links.txt
raptus.article.gallery.egg-info/entry_points.txt
raptus.article.gallery.egg-info/namespace_packages.txt
raptus.article.gallery.egg-info/not-zip-safe
raptus.article.gallery.egg-info/requires.txt
raptus.article.gallery.egg-info/top_level.txt
raptus/article/__init__.py
raptus/article/gallery/__init__.py
raptus/article/gallery/configure.zcml
raptus/article/gallery/browser/__init__.py
raptus/article/gallery/browser/configure.zcml
raptus/article/gallery/browser/gallery.js
raptus/article/gallery/browser/gallery.pt
raptus/article/gallery/browser/gallery.py
raptus/article/gallery/browser/gallery_columns.gif
raptus/article/gallery/browser/gallery_left.gif
raptus/article/gallery/browser/gallery_right.gif
raptus/article/gallery/i18n/raptus.article-de.mo
raptus/article/gallery/i18n/raptus.article-de.po
raptus/article/gallery/i18n/raptus.article-fr.mo
raptus/article/gallery/i18n/raptus.article-fr.po
raptus/article/gallery/i18n/raptus.article-it.mo
raptus/article/gallery/i18n/raptus.article-it.po
raptus/article/gallery/i18n/raptus.article.pot
raptus/article/gallery/profiles/default/cssregistry.xml
raptus/article/gallery/profiles/default/jsregistry.xml
raptus/article/gallery/profiles/default/metadata.xml
raptus/article/gallery/profiles/default/propertiestool.xml
raptus/article/gallery/profiles/default/skins.xml
raptus/article/gallery/profiles/default/viewlets.xml
raptus/article/gallery/skins/raptus_article_gallery/raptus.article.gallery.css.dtml
raptus/article/gallery/upgrades/__init__.py
raptus/article/gallery/upgrades/configure.zcml
raptus/article/gallery/upgrades/profiles.zcml
raptus/article/gallery/upgrades/profiles/0003_to_0004/propertiestool.xml