Metadata-Version: 1.1
Name: raptus.article.gallery
Version: 2.0b11
Summary: Provides basic gallery components.
Home-page: https://github.com/Raptus/raptus.article.gallery
Author: Raptus AG
Author-email: dev@raptus.com
License: GPL
Platform: UNKNOWN
Classifier: Programming Language :: Python
Classifier: Topic :: Software Development :: Libraries :: Python Modules
